willminds/__init__.py
willminds/data/__init__.py
willminds/data/corpus/MiniMindVL_dataset.py
willminds/data/corpus/MiniMind_dataset.py
willminds/data/corpus/__init__.py
willminds/data/loader/__init__.py
willminds/model/__init__.py
willminds/model/framework/__init__.py
willminds/model/framework/MiniMind/__init__.py
willminds/model/framework/MiniMind/configuration_MiniMind.py
willminds/model/framework/MiniMind/modeling_MiniMind.py
willminds/model/framework/MiniMindVL/__init__.py
willminds/model/framework/MiniMindVL/configuration_MiniMindVL.py
willminds/model/framework/MiniMindVL/modeling_MiniMindVL.py
willminds/model/module/CR_CNN.py
willminds/model/module/__init__.py
willminds/model/module/globalpointer.py
willminds/model/module/torchcrf.py
willminds/model/module/Attention/__init__.py
willminds/model/module/Attention/vanilla_attention.py
willminds/model/module/Embedding/RoPE.py
willminds/model/module/Embedding/__init__.py
willminds/model/module/FeedForward/__init__.py
willminds/model/module/FeedForward/vanilla_feedforward.py
willminds/model/module/LoRA/__init__.py
willminds/model/module/LoRA/vanilla_lora.py
willminds/model/module/Norm/ConditionalLayerNorm.py
willminds/model/module/Norm/RMSNorm.py
willminds/model/module/Norm/__init__.py
willminds/model/tokenizer/__init__.py
willminds/monitor/__init__.py
willminds/monitor/config/__init__.py
willminds/monitor/logging/__init__.py
willminds/monitor/tracking/__init__.py
willminds/optim/__init__.py
willminds/optim/loss/PairwiseRankingLoss.py
willminds/optim/loss/__init__.py
willminds/optim/optimizer/__init__.py
willminds/pipeline/MiniMind_trainer.py
willminds/pipeline/__init__.py
willminds/pipeline/deprecated/evaluate.py
willminds/utils/__init__.py
willminds/utils/filesystem.py
willminds/utils/io_stream.py
willminds/utils/parse.py
willminds/utils/simple_operation.py
willminds/utils/threading_n.py
willminds-0.0.1.dist-info/licenses/LICENSE
willminds-0.0.1.dist-info/METADATA
willminds-0.0.1.dist-info/WHEEL
willminds-0.0.1.dist-info/top_level.txt
willminds-0.0.1.dist-info/RECORD
