Metadata-Version: 2.4
Name: willminds
Version: 0.0.1
Summary: Explore to building the intelligence easily! It's based on Torch, Transformers, etc.
Author-email: Mengsong Wu <radi.cat@qq.com>
Maintainer-email: Mengsong Wu <radi.cat@qq.com>
License: MIT License
Project-URL: Homepage, https://github.com/fairyshine/WillMindS.AI/
Project-URL: Bug Tracker, https://github.com/fairyshine/WillMindS.AI/issues
Project-URL: Source, https://github.com/fairyshine/WillMindS.AI
Requires-Python: >=3.10
License-File: LICENSE
Requires-Dist: rich
Requires-Dist: omegaconf
Requires-Dist: numpy
Dynamic: license-file
